Metadata-Version: 2.1
Name: rezolva
Version: 0.3.0
Summary: Entity resolution for everyone. Minimal. No dependencies.
Home-page: https://github.com/joshmeek/rezolva
Author: Josh Meek
Author-email: mail@josh.dev
Classifier: Programming Language :: Python :: 3
Classifier: License :: OSI Approved :: MIT License
Requires-Python: >=3.7
License-File: LICENSE
